dreem_herschlag/__init__.py
dreem_herschlag/add_info.py
dreem_herschlag/export.py
dreem_herschlag/folder_converter.py
dreem_herschlag/generate_mh_only.py
dreem_herschlag/get_info.py
dreem_herschlag/poisson.py
dreem_herschlag/rnastructure.py
dreem_herschlag/run.py
dreem_herschlag/run_dreem.py
dreem_herschlag/sanity_check.py
dreem_herschlag/templates.py
dreem_herschlag/util.py
dreem_herschlag/resources/__init__.py
dreem_herschlag/resources/config-template.yml
dreem_herschlag/resources/library_attributes.yml
dreem_herschlag/resources/sample_attributes.yml
dreem_herschlag-1.1.9.dist-info/LICENSE
dreem_herschlag-1.1.9.dist-info/METADATA
dreem_herschlag-1.1.9.dist-info/WHEEL
dreem_herschlag-1.1.9.dist-info/entry_points.txt
dreem_herschlag-1.1.9.dist-info/top_level.txt
dreem_herschlag-1.1.9.dist-info/RECORD
