Metadata-Version: 2.1
Name: dreem-herschlag
Version: 1.1.9
Summary: A wrapper for DREEM for the Herschlag lab
Home-page: https://github.com/yvesmartindestaillades/dreem_herschlag
Author: Yves Martin des Taillades
Author-email: yves@martin.yt
License: MIT
Platform: UNKNOWN
License-File: LICENSE
Requires-Dist: attrs (==22.1.0)
Requires-Dist: biopython (==1.79)
Requires-Dist: build (==0.8.0)
Requires-Dist: click (==8.1.3)
Requires-Dist: click-option-group (==0.5.3)
Requires-Dist: colorlog (==6.6.0)
Requires-Dist: cycler (==0.11.0)
Requires-Dist: dunamai (==1.12.0)
Requires-Dist: fonttools (==4.34.4)
Requires-Dist: future (==0.18.2)
Requires-Dist: get-version (==3.5.4)
Requires-Dist: iniconfig (==1.1.1)
Requires-Dist: kiwisolver (==1.4.4)
Requires-Dist: matplotlib (==3.5.2)
Requires-Dist: numpy (==1.23.1)
Requires-Dist: packaging (==21.3)
Requires-Dist: pandas (==1.4.3)
Requires-Dist: pep517 (==0.13.0)
Requires-Dist: pillow (==9.2.0)
Requires-Dist: pip-tools (==6.8.0)
Requires-Dist: plotly (==5.9.0)
Requires-Dist: pluggy (==1.0.0)
Requires-Dist: py (==1.11.0)
Requires-Dist: pyparsing (==3.0.9)
Requires-Dist: pytest (==7.1.2)
Requires-Dist: python-dateutil (==2.8.2)
Requires-Dist: pytz (==2022.1)
Requires-Dist: pyyaml (==6.0)
Requires-Dist: scipy (==1.9.0)
Requires-Dist: six (==1.16.0)
Requires-Dist: tabulate (==0.8.10)
Requires-Dist: tenacity (==8.0.1)
Requires-Dist: tomli (==2.0.1)
Requires-Dist: wheel (==0.37.1)
